minienv/cli.py
minienv/constants.py
minienv/launcher.py
minienv/runner.py
minienv/backend/__init__.py
minienv/backend/adapter.py
minienv/backend/beaker.py
minienv/backend/local.py
minienv/examples/swebench/beaker_env.py
minienv/examples/swebench/swebench.py
minienv/examples/swebench/swebench_single.py
minienv/examples/tbench/build_images.py
minienv/examples/tbench/minienv_terminal.py
minienv/examples/tbench/tb.py
minienv/server/main.py
minienv-0.1.3.dist-info/METADATA
minienv-0.1.3.dist-info/WHEEL
minienv-0.1.3.dist-info/entry_points.txt
minienv-0.1.3.dist-info/top_level.txt
minienv-0.1.3.dist-info/RECORD
